azure_datalake_logging/__init__.py
azure_datalake_logging/py.typed
azure_datalake_logging/utils.py
azure_datalake_logging/formatters/__init__.py
azure_datalake_logging/formatters/base_formatter.py
azure_datalake_logging/formatters/json_formatter.py
azure_datalake_logging/formatters/struct_formatter.py
azure_datalake_logging/handlers/__init__.py
azure_datalake_logging/handlers/base_handler.py
azure_datalake_logging/handlers/blob_handler.py
azure_datalake_logging/handlers/queue_handler.py
azure_datalake_logging/handlers/table_handler.py
azure_datalake_logging/models/__init__.py
azure_datalake_logging-1.0.1.dist-info/METADATA
azure_datalake_logging-1.0.1.dist-info/WHEEL
azure_datalake_logging-1.0.1.dist-info/licenses/LICENSE
azure_datalake_logging-1.0.1.dist-info/RECORD
