Metadata-Version: 2.4
Name: azure-datalake-logging
Version: 1.0.1
Summary: Write your logs to Azure Storage (e.g., Blob, Queue, and Table)
Author-email: Markus Feiks <pypi.packages@feyx.de>
License-File: LICENSE
Requires-Python: >=3.10
Requires-Dist: azure-data-tables>=12.6.0
Requires-Dist: azure-identity>=1.21.0
Requires-Dist: multidict>=6.4.3
Requires-Dist: uuid-extension>=0.0.3
